{
  "code": 0,
  "data": [
    {
      "title": "北京市海淀区一在建工地发生事故",
      "time": "2019-03-13",
      "site": "海淀区",
      "name": "张某某",
      "state": "已上报",
      "type": "建设工程事故"
    },
    {
      "title": "北京市海淀区一在建工地发生事故",
      "time": "2019-03-13",
      "site": "海淀区",
      "name": "张某某",
      "state": "已上报",
      "type": "建设工程事故"
    },
    {
      "title": "北京市海淀区一在建工地发生事故",
      "time": "2019-03-13",
      "site": "海淀区",
      "name": "张某某",
      "state": "已上报",
      "type": "建设工程事故"
    },
    {
      "title": "北京市海淀区一在建工地发生事故",
      "time": "2019-03-13",
      "site": "海淀区",
      "name": "张某某",
      "state": "已上报",
      "type": "建设工程事故"
    },
    {
      "title": "北京市海淀区一在建工地发生事故",
      "time": "2019-03-13",
      "site": "海淀区",
      "name": "张某某",
      "state": "已上报",
      "type": "建设工程事故"
    },
    {
      "title": "北京市海淀区一在建工地发生事故",
      "time": "2019-03-13",
      "site": "海淀区",
      "name": "张某某",
      "state": "已上报",
      "type": "建设工程事故"
    },
    {
      "title": "北京市海淀区一在建工地发生事故",
      "time": "2019-03-13",
      "site": "海淀区",
      "name": "张某某",
      "state": "已上报",
      "type": "建设工程事故"
    },
    {
      "title": "北京市海淀区一在建工地发生事故",
      "time": "2019-03-13",
      "site": "海淀区",
      "name": "张某某",
      "state": "已上报",
      "type": "建设工程事故"
    },
    {
      "title": "北京市海淀区一在建工地发生事故",
      "time": "2019-03-13",
      "site": "海淀区",
      "name": "张某某",
      "state": "已上报",
      "type": "建设工程事故"
    },
    {
      "title": "北京市海淀区一在建工地发生事故",
      "time": "2019-03-13",
      "site": "海淀区",
      "name": "张某某",
      "state": "已上报",
      "type": "建设工程事故"
    }
  ]
}